bugscanx/__init__.py
bugscanx/auto_updater.py
bugscanx/dns_info.py
bugscanx/host_scanner.py
bugscanx/import_modules.py
bugscanx/ip_lookup.py
bugscanx/ip_scan.py
bugscanx/main.py
bugscanx/open_port.py
bugscanx/osint.py
bugscanx/pkg_remover.py
bugscanx/script_help.py
bugscanx/setp.py
bugscanx/sub_finder.py
bugscanx/sub_scan.py
bugscanx/txt_toolkit.py
BugScanX-1.2.2.dist-info/LICENSE
BugScanX-1.2.2.dist-info/METADATA
BugScanX-1.2.2.dist-info/WHEEL
BugScanX-1.2.2.dist-info/entry_points.txt
BugScanX-1.2.2.dist-info/top_level.txt
BugScanX-1.2.2.dist-info/RECORD
