Metadata-Version: 2.1
Name: BugScanX
Version: 1.2.2
Summary: All in one toolkit for SNI bughost analysis
Home-page: https://github.com/ayanrajpoot10/BugScanX
Author: Ayan Rajpoot
Author-email: ayanrajpoot2004@gmail.com
License: MIT
Classifier: Programming Language :: Python :: 3
Classifier: License :: OSI Approved :: MIT License
Classifier: Operating System :: OS Independent
Requires-Python: >=3.6
License-File: LICENSE
